mdocument/__init__.py
mdocument/client.py
mdocument/document.py
mdocument/document_array.py
mdocument/document_dict.py
mdocument/exceptions.py
mdocument/model/__init__.py
mdocument/model/field.py
mdocument/model/index.py
mdocument/model/model.py
mdocument/model/relations.py
mdocument-4.0.1612576120.dist-info/LICENSE
mdocument-4.0.1612576120.dist-info/METADATA
mdocument-4.0.1612576120.dist-info/WHEEL
mdocument-4.0.1612576120.dist-info/top_level.txt
mdocument-4.0.1612576120.dist-info/RECORD
