Metadata-Version: 2.1
Name: mdocument
Version: 4.0.1612576120
Summary: Simple DRM for motor client
Home-page: https://git.yurzs.dev/yurzs/MDocument
Author: Yurzs
Author-email: yurzs+mdocument@yurzs.dev
License: MIT
Keywords: mongo,motor,Document,ORM
Platform: UNKNOWN
Classifier: Development Status :: 3 - Alpha
Classifier: License :: OSI Approved :: MIT License
Classifier: Programming Language :: Python :: 3.6
Classifier: Programming Language :: Python :: 3.7
Classifier: Programming Language :: Python :: 3.8
Requires-Dist: motor
